limesurveyrc2api/__init__.py
limesurveyrc2api/_survey.py
limesurveyrc2api/_token.py
limesurveyrc2api/exceptions.py
limesurveyrc2api/limesurvey.py
limesurveyrc2api-2.0.0.dist-info/LICENSE
limesurveyrc2api-2.0.0.dist-info/METADATA
limesurveyrc2api-2.0.0.dist-info/WHEEL
limesurveyrc2api-2.0.0.dist-info/top_level.txt
limesurveyrc2api-2.0.0.dist-info/RECORD
