Metadata-Version: 2.1
Name: limesurveyrc2api
Version: 2.0.0
Summary: LimeSurvey RC2 API Web Services Client
Home-page: https://github.com/lindsay-stevens
Author: Lindsay Stevens
Author-email: lindsay.stevens.au@gmail.com
License: MIT
Keywords: limesurvey api webservice client
Platform: UNKNOWN
Classifier: Development Status :: 5 - Production/Stable
Classifier: Intended Audience :: Developers
Classifier: License :: OSI Approved :: MIT License
Classifier: Programming Language :: Python :: 3.9
License-File: LICENSE
Requires-Dist: requests (==2.28.2)
